{
    "FE" : {
      "Language": [
        {
            "name" : "JavaScript",
            "level" : 3
        },
        {
            "name" : "TypeScript",
            "level" : 3
        }
      ],
     "LibraryOrFramework":[
        {
            "name" : "React",
            "level" : 3
        },
        {
            "name" : "NextJS",
            "level" : 3
        },
        {
            "name" : "Redux",
            "level" : 2
        },
        {
            "name" : "Recoil",
            "level" : 3
        },
        {
            "name" : "React-Query",
            "level" : 2
        }
     ],
     "Style": [
        {
            "name" : "Styled-Components",
            "level" : 3
        },
        {
            "name" : "TailwindCSS", 
            "level" : 2
        },
        {
            "name" : "Antd",
            "level" : 3
        },
        {
            "name" : "Bootstrap",
            "level" : 3
        }
     ],
     "Test": [
        {
            "name" : "Jest",
            "level" : 2
        },
        {
            "name" : "StoryBook",
            "level" : 2
        },
        {   
            "name" : "Playwright",
            "level" : 3
        }
     ],
     "Package": [
        {
            "name" : "npm",
            "level" : 3
        },
        {
            "name" : "yarn",
            "level" : 3
        },
        {
            "name" : "pnpm",
            "level" : 3
        }
     ],
     "Format": [
        {
            "name" : "ESLint",
            "level" : 2
        },
        {
            "name" : "Prettier",
            "level" : 2
        }
     ]
    },
    "BE" : {
        "Language": [
            {
                "name" : "JavaScript",
                "level" : 3
            },
            {
                "name" : "TypeScript",
                "level" : 3
            }
         ],
         "LibraryOrFramework":[
            {
                "name" : "Node.JS",
                "level" : 2
            },
            {
                "name" : "Express",
                "level" : 2
            },
            {
                "name" : "SWR",
                "level" : 1
            },
            {
                "name" : "TypeORM",
                "level" : 1
            }
         ],
         "Database": [
            {
                "name" : "PostgreSQL",
                "level" : 2
            },
            {
                "name" : "MongoDB", 
                "level" : 2
            },
            {
                "name" : "Firebase",
                "level" : 2
            }
         ]
    },
    "DevOps" : [
        {
            "name" : "Github Action",
            "level" : 3
        },
        {
            "name" : "Docker",
            "level" : 2
        },
        {
            "name" : "AWS EC2",
            "level" : 2
        },
        {
            "name" : "AWS S3",
            "level" : 2
        },
        {   
            "name" : "Vercel",
            "level" : 3
        }
    ],
    "Communication" : [
        {
            "name" : "Slack",
            "level" : 4
        },
        {
            "name" : "ClickUp",
            "level" : 3
        },
        {
            "name" : "Figma",
            "level" : 3
        }
    ]
}